env_config_lib/__init__.py
env_config_lib/env_config.py
env_config_lib-0.1.1.dist-info/METADATA
env_config_lib-0.1.1.dist-info/WHEEL
env_config_lib-0.1.1.dist-info/top_level.txt
env_config_lib-0.1.1.dist-info/RECORD
