Metadata-Version: 2.4
Name: env-config-lib
Version: 0.1.1
Summary: Удобная работа с переменными окружения через схему
Author-email: Timur <freyzan2006@gmail.com>
License: MIT
Requires-Python: >=3.8
Requires-Dist: python-dotenv
